vxquant/__init__.py
vxquant/__providers/__init__.py
vxquant/__providers/dataloaders.py
vxquant/__providers/tencenthq.py
vxquant/base.py
vxquant/constants.py
vxquant/exceptions.py
vxquant/mdapis/__init__.py
vxquant/mdapis/local.py
vxquant/models.py
vxquant/portfolio.py
vxquant/scripts/__init__.py
vxquant/scripts/run.py
vxquant/scripts/system.py
vxquant/strategys/__init__.py
vxquant/strategys/netgrid.py
vxquant/tdapis/__init__.py
vxquant/tdapis/miniqmt.py
vxquant-20240902.dist-info/entry_points.txt
vxquant-20240902.dist-info/METADATA
vxquant-20240902.dist-info/WHEEL
vxquant-20240902.dist-info/RECORD
